{"attribution":"http://www.bjxbsj.cn","available":[[{"endX":1,"endY":0,"startX":0,"startY":0}],[{"endX":3,"endY":1,"startX":0,"startY":0}],[{"endX":7,"endY":3,"startX":0,"startY":0}],[{"endX":15,"endY":7,"startX":0,"startY":0}],[{"endX":31,"endY":15,"startX":0,"startY":2}],[{"endX":53,"endY":23,"startX":52,"startY":22}],[{"endX":105,"endY":45,"startX":104,"startY":44}],[{"endX":209,"endY":89,"startX":208,"startY":88}],[{"endX":417,"endY":179,"startX":416,"startY":178}],[{"endX":835,"endY":359,"startX":834,"startY":358}],[{"endX":1671,"endY":719,"startX":1668,"startY":718}],[{"endX":3341,"endY":1437,"startX":3338,"startY":1436}],[{"endX":6681,"endY":2875,"startX":6678,"startY":2874}],[{"endX":13361,"endY":5751,"startX":13358,"startY":5750},{"endX":13363,"endY":5751,"startX":13362,"startY":5750}],[{"endX":26721,"endY":11503,"startX":26718,"startY":11500},{"endX":26725,"endY":11503,"startX":26722,"startY":11500}],[{"endX":53443,"endY":23005,"startX":53436,"startY":23000},{"endX":53449,"endY":23005,"startX":53444,"startY":23000}],[{"endX":106887,"endY":46011,"startX":106874,"startY":46000},{"endX":106897,"endY":46011,"startX":106888,"startY":46000}],[{"endX":213773,"endY":92023,"startX":213750,"startY":92000},{"endX":213795,"endY":92023,"startX":213774,"startY":92000}],[{"endX":427547,"endY":184045,"startX":427500,"startY":184002},{"endX":427591,"endY":184045,"startX":427548,"startY":184002}],[{"endX":855093,"endY":368091,"startX":855002,"startY":368006},{"endX":855181,"endY":368091,"startX":855094,"startY":368006}]],"bounds":[-180,-90,180,90],"description":"http://www.bjxbsj.cn","extensions":["octvertexnormals"],"format":"quantized-mesh-1.0","maxzoom":19,"metadataAvailability":10,"minzoom":0,"name":"world","projection":"EPSG:4326","scheme":"tms","tilejson":"1.0","tiles":["{z}/{x}/{y}.terrain"],"valid_bounds":[113.54212135076523,36.34544759988785,113.60315769910812,36.37382537126541],"version":"1.0.0"}